maser/data/__init__.py
maser/data/base/__init__.py
maser/data/base/base.py
maser/data/base/cdf_fill.py
maser/data/base/class_factory.py
maser/data/base/dataset_filename_regex.json
maser/data/base/mixins.py
maser/data/base/records.py
maser/data/base/sweeps.py
maser/data/cdpp/__init__.py
maser/data/cdpp/ccsds.py
maser/data/cdpp/const.py
maser/data/cdpp/interball/__init__.py
maser/data/cdpp/interball/data.py
maser/data/cdpp/interball/records.py
maser/data/cdpp/interball/sweeps.py
maser/data/cdpp/stereo/__init__.py
maser/data/cdpp/stereo/data.py
maser/data/cdpp/stereo/sweeps.py
maser/data/cdpp/utils.py
maser/data/cdpp/viking/__init__.py
maser/data/cdpp/viking/const.py
maser/data/cdpp/viking/data.py
maser/data/cdpp/viking/records.py
maser/data/cdpp/wind/__init__.py
maser/data/cdpp/wind/data.py
maser/data/cdpp/wind/records.py
maser/data/cdpp/wind/sweeps.py
maser/data/ecallisto/__init__.py
maser/data/ecallisto/data.py
maser/data/nancay/__init__.py
maser/data/nancay/nda/__init__.py
maser/data/nancay/nda/data.py
maser/data/nancay/nda/sweeps.py
maser/data/nancay/nenufar/__init__.py
maser/data/nancay/nenufar/data.py
maser/data/padc/__init__.py
maser/data/padc/bepi/__init__.py
maser/data/padc/bepi/sorbet/__init__.py
maser/data/padc/bepi/sorbet/data.py
maser/data/padc/cassini/__init__.py
maser/data/padc/cassini/data.py
maser/data/padc/cassini/kronos.py
maser/data/padc/cassini/kronos_level_format.json
maser/data/padc/expres/__init__.py
maser/data/padc/expres/data.py
maser/data/padc/expres/sweeps.py
maser/data/padc/juice/__init__.py
maser/data/padc/juice/rpwi/__init__.py
maser/data/padc/juice/rpwi/data.py
maser/data/padc/juice/rpwi/sweeps.py
maser/data/padc/juno/__init__.py
maser/data/padc/juno/data.py
maser/data/padc/solo/__init__.py
maser/data/padc/solo/rpw/__init__.py
maser/data/padc/solo/rpw/data.py
maser/data/padc/solo/rpw/hfr.py
maser/data/padc/solo/rpw/lfr.py
maser/data/padc/solo/rpw/tnr.py
maser/data/padc/solo/rpw/tnr_filter.py
maser/data/padc/stereo/__init__.py
maser_data-0.5.1.dist-info/METADATA
maser_data-0.5.1.dist-info/WHEEL
maser_data-0.5.1.dist-info/RECORD
