Metadata-Version: 2.3
Name: maser-data
Version: 0.5.1
Summary: Maser4py submodule to handle radio data
License: CECILL-B
Author: Baptiste Cecconi
Author-email: baptiste.cecconi@obspm.fr
Requires-Python: >=3.9,<4
Classifier: License :: CeCILL-B Free Software License Agreement (CECILL-B)
Classifier: Programming Language :: Python :: 3
Classifier: Programming Language :: Python :: 3.9
Classifier: Programming Language :: Python :: 3.10
Classifier: Programming Language :: Python :: 3.11
Classifier: Programming Language :: Python :: 3.12
Classifier: Programming Language :: Python :: 3.13
Provides-Extra: all
Provides-Extra: jupyter
Provides-Extra: spacepy
Requires-Dist: astropy (>=5.0.4,<6.0.0)
Requires-Dist: jupyter (>=1.0.0,<2.0.0) ; extra == "jupyter" or extra == "all"
Requires-Dist: jupytext (>=1.13.8,<2.0.0) ; extra == "jupyter" or extra == "all"
Requires-Dist: numpy (>=1.26,<2)
Requires-Dist: spacepy (>=0.5,<1.0) ; extra == "spacepy" or extra == "all"
Requires-Dist: xarray (>=2022.3.0,<2023.0.0)
